{
  "id": "BUG-006",
  "type": "bug",
  "category": "VS Code Extension",
  "title": "Hide Done toggle not working in hierarchical view",
  "status": "done",
  "eisenhower": "urgent-important",
  "created": "2025-11-24T12:45:53.890Z",
  "updated": "2025-11-24T12:59:41.113Z",
  "author": "the@devsteps.dev",
  "affected_paths": [
    "packages/vscode-extension/src/treeView/devstepsTreeDataProvider.ts"
  ],
  "linked_items": {
    "implements": [],
    "implemented-by": [],
    "tested-by": [],
    "tests": [],
    "blocks": [],
    "blocked-by": [],
    "relates-to": [
      "TASK-031"
    ],
    "depends-on": [],
    "required-by": [],
    "supersedes": [],
    "superseded-by": []
  },
  "tags": [
    "bug",
    "treeview",
    "filter",
    "hierarchical-view",
    "toggle"
  ],
  "commits": [],
  "metadata": {}
}
