{
  "id": "BUG-018",
  "type": "bug",
  "category": "general",
  "title": "Verify all 8 status badges are correctly implemented",
  "status": "obsolete",
  "eisenhower": "urgent-important",
  "created": "2025-11-27T16:35:29.832Z",
  "updated": "2025-11-27T16:37:39.906Z",
  "author": "the@devsteps.dev",
  "affected_paths": [
    "packages/extension/src/decorationProvider.ts"
  ],
  "linked_items": {
    "implements": [],
    "implemented-by": [],
    "tested-by": [],
    "tests": [],
    "blocks": [],
    "blocked-by": [],
    "relates-to": [
      "BUG-017",
      "TASK-007",
      "TASK-009"
    ],
    "depends-on": [],
    "required-by": [],
    "supersedes": [],
    "superseded-by": []
  },
  "tags": [
    "vscode",
    "badges",
    "decoration",
    "colors",
    "ui"
  ],
  "commits": [],
  "metadata": {}
}
