{
  "id": "TASK-062",
  "type": "task",
  "category": "vscode",
  "title": "Implement CSV Export - Structured Data for Analysis",
  "status": "draft",
  "eisenhower": "not-urgent-not-important",
  "created": "2025-11-26T06:53:23.777Z",
  "updated": "2025-11-26T06:53:30.140Z",
  "author": "the@devsteps.dev",
  "affected_paths": [
    "packages/extension/src/webview/dashboardPanel.ts"
  ],
  "linked_items": {
    "implements": [
      "STORY-018"
    ],
    "implemented-by": [],
    "tested-by": [],
    "tests": [],
    "blocks": [],
    "blocked-by": [],
    "relates-to": [],
    "depends-on": [],
    "required-by": [],
    "supersedes": [],
    "superseded-by": []
  },
  "tags": [
    "export",
    "csv",
    "data"
  ],
  "commits": [],
  "metadata": {}
}
