{
  "id": "TASK-132",
  "type": "task",
  "category": "devops",
  "title": "Fix MCP Server & CLI TypeScript Build Configuration",
  "status": "done",
  "eisenhower": "urgent-important",
  "created": "2025-12-03T16:22:27.621Z",
  "updated": "2025-12-03T16:22:36.571Z",
  "author": "the@devsteps.dev",
  "affected_paths": [
    "packages/mcp-server/tsconfig.json",
    "packages/mcp-server/src/handlers/add.ts",
    "packages/mcp-server/src/handlers/update.ts",
    "packages/cli/package.json",
    ".devsteps/tasks/TASK-138.md"
  ],
  "linked_items": {
    "implements": [
      "STORY-038"
    ],
    "implemented-by": [],
    "tested-by": [],
    "tests": [],
    "blocks": [],
    "blocked-by": [],
    "relates-to": [
      "TASK-083",
      "TASK-084"
    ],
    "depends-on": [],
    "required-by": [
      "TASK-131"
    ],
    "supersedes": [],
    "superseded-by": []
  },
  "tags": [
    "mcp-server",
    "cli",
    "typescript",
    "build",
    "npm",
    "critical-fix"
  ],
  "commits": [],
  "metadata": {}
}
